{
  "note_id": "692113f0000000001e03ac4e",
  "type": "normal",
  "title": "冰雪大世界-鬼斧神工的冰雕艺术",
  "desc": "在祖国东北的怀抱中，有一座城市宛如一颗璀璨的明珠，它就是被誉为“冰城”的哈尔滨。而哈尔滨冰雪大世界，则是这座城市冬季里最耀眼的瑰宝，其中的冰雕艺术更是鬼斧神工，令人叹为观止。\\n哈尔滨冰雪大世界始创于1999年，是由哈尔滨市政府为迎接千年庆典神州世纪游活动而推出的大型冰雪艺术精品工程。这里拥有得天独厚的自然条件，寒冷漫长的冬季为冰雕艺术的创作提供了绝佳的环境。\\n冰雪大世界的冰雕艺术，首先源于优质的原料。松花江的江水清澈，水流稳定，形成的冰层密度均匀，裂纹少，透明度高，为冰雕提供了最佳的材质基础。冰雕师傅们会精心挑选这些冰块，然后运用各种工具，如油锯、刨刃、冰铲、冰镩等，将它们雕刻成形态各异的艺术品。\\n冰雕的制作过程是一项极其复杂和精细的工艺。冰雕师傅们需要根据设计图纸，先用油锯将冰块切割成合适的大小和形状，这一步需要极高的精确度，因为每一块冰料的形状和大小都会直接影响到最终作品的呈现效果。接着，他们会用冰镩等工具下大块冰料，勾勒出作品的大致轮廓。然后，再换上更精细的雕刻工具，如刻刀、砂轮等，进行精雕细琢。在这个过程中，师傅们需要不断调整角度和力度，以确保每一个细节都完美无瑕。例如，在雕刻马头时，师傅们会用最小的工具刀，小心翼翼地雕琢出马头的神清骨峻、长鬃飞扬的细节，让马头仿佛有了生命一般。\\n当所有的冰料都雕刻完成后，师傅们会开始组合和拼接。他们用水作为粘合剂，将冰块巧妙地粘合在一起，形成巍峨的冰建筑或精巧的冰工艺品。这一步需要极高的技巧和经验，因为冰块的拼接必须严丝合缝，否则会影响作品的稳定性和美观性。最后，师傅们还会用冰铲将冰雕上多余的冰溜子一一清除，让冰雕更加完美。\\n冰雪大世界的冰雕作品种类繁多，形态各异。有雄伟壮观的冰建筑，如主塔“冰雪同梦”，它以冰雪与心形相互交织的形态，象征着亚洲各国各地区有着同样的冰雪梦想；还有仿照古代宫殿的冰雕，飞檐翘角在冰的雕琢下细腻入微，每一道纹路都栩栩如生，仿佛在讲述着古代皇室的庄重与辉煌。也有栩栩如生的冰雕动物，如玉兔、大象、熊猫等，它们形态逼真，活泼可爱，在彩灯的照射下，亦动亦静，惟妙惟肖。此外，还有各种抽象创意造型的冰雕，如彩色冰雕作品，这些作品由新研发的“植物有色冰”制成，色彩柔和、耐看，还不掉色，让冰雕艺术呈现出更加丰富的外形与内涵。",
  "user_id": "",
  "has_image": false,
  "has_video": false,
  "images": [],
  "video": ""
}