{
  "note_id": "69270aa7000000001e0005ca",
  "type": "normal",
  "title": "尔滨会冻坏每一个不认真做攻略的人…🥹🥹",
  "desc": "作为土生土长的黑龙江孩子，真的会反复爱上冬天的哈尔滨！去哈尔滨n次，总结这篇攻略，能救一个是一个…😳😳\\n1️⃣不要住中央大街附近！溢价厉害且住宿环境差！性价比非常低！\\n2️⃣避雷天价租装服，自己穿厚点就行！多贴暖宝宝！提前网上买加热鞋垫，脚底下暖洋洋身上也跟着暖和！\\n3️⃣别理会机场/火车站门口的黑车！机场到市区大巴25r直达，黑车张口就要80+且是拼车还没保障！\\n4️⃣市内交通尽可能选网约车或地铁，地铁3号线能到大部分景点！\\n5️⃣别坐路边的拉客小车！尤其去冰雪大世界，张口就几十！冰雪大世界返程最好提前约网约车或坐公交211，不要排队等出租，在寒风里冻到怀疑人生！\\n6️⃣没必要起大早去红砖街早市！跟普通早市没区别！价格高的离谱，产品没有东北特色且早上去很冷！\\n7️⃣道里菜市场才是正宗东北烟火气！在室内很暖和而且品类全！价格实惠口味正宗，冬季人多时会限流要排队，但也非常值得！\\n8️⃣冰雪大世界最好下午三点半进场，先去拍没人的冰雕，晚上看烟花和无人机表演（不要挤在主舞台！侧面视角更绝）\\n9️⃣冰雪大世界里消费偏高！一杯热水要10r！最好自带零食、保温杯热水，怕冷就多贴几贴暖宝宝！\\n🔟索菲亚教堂早8点前去，没人！阳光倾斜在洋葱顶上巨出片！下午人多，适合坐下来听音乐喷泉。最好和道里菜市场安排在同一个上午，逛完菜市场一出门就到～\\n1️⃣1️⃣喜欢复古建筑的老道外必冲！中华巴洛克建筑，都是百年前老房子，保存尚好，随便逛都是烟火气，比中央大街人少！\\n1️⃣2️⃣中央大街马迭尔冰棍别买联名款，价格高且不正宗！原味5r的才最经典！\\n1️⃣3️⃣买哈尔滨红肠选秋林公司、商委红肠都可，商委得早起排队，秋林可以快递，别在中央大街买花里胡哨的，价格高味道还不正宗！\\n1️⃣4️⃣景点门票能提前网上买就提前买，现场排队冻到怀疑人生！冰雪大世界学生证可以半价！\\n1️⃣5️⃣别穿太笨重的鞋子！雪地靴就选防滑的，很多冰面很滑，一不小心摔个屁股蹲都是常事儿！\\n1️⃣6️⃣想看免费冰雕可以去兆麟公园，晚上去有灯光！\\n1️⃣7️⃣不要跟团不要跟团！网上跟团避雷一抓一大把！自己规划好行程玩的会很自在～\\n\\t\\n下篇3天2晚行程及美食推荐，需要的小宝可以蹲一蹲～\\n\\t\\n#哈尔滨[话题]# #哈尔滨旅行[话题]# #哈尔滨旅游[话题]# #哈尔滨旅行攻略[话题]# #哈尔滨旅游攻略[话题]# #哈尔滨美食[话题]#",
  "user_id": "",
  "has_image": false,
  "has_video": false,
  "images": [],
  "video": ""
}